[
  {
    "_id": "5bd789bb626daf74460af34b",
    "constant": "false",
    "payable": "false",
    "error": null,
    "task_display": "Define a confirmTransaction function",
    "name": "confirmTransaction",
    "inputs": [
      {
        "_id": "5bd789bb626daf74460af34c",
        "name": null,
        "staticType": "uint256"
      }
    ],
    "interfaceType": "function"
  },
  {
    "_id": "5bd789bb626daf74460af34d",
    "constant": "true",
    "payable": "false",
    "error": null,
    "task_display": "Define a validOwners mapping",
    "name": "validOwners",
    "outputs": [
      {
        "_id": "5bd789bb626daf74460af34e",
        "name": null,
        "staticType": "bool"
      }
    ],
    "inputs": [
      {
        "_id": "5bd789bb626daf74460af34f",
        "name": null,
        "staticType": "address"
      }
    ],
    "interfaceType": "function"
  }
]